Metadata-Version: 2.1
Name: log-handler-daily-path
Version: 0.0.3
Summary: This module is a log handler by daily path rotating.
Home-page: https://github.com/meanstrong/log-handler-daily-path
Author: Rocky Peng
Author-email: rockypengchina@outlook.com
Maintainer: Rocky Peng
Maintainer-email: rockypengchina@outlook.com
License: GPLv3
Platform: any
Classifier: Programming Language :: Python
Classifier: Programming Language :: Python :: 3
